reqs2brew/__init__.py
reqs2brew/generate_resources.py
reqs2brew-0.1.2.dist-info/licenses/LICENSE
reqs2brew-0.1.2.dist-info/METADATA
reqs2brew-0.1.2.dist-info/WHEEL
reqs2brew-0.1.2.dist-info/entry_points.txt
reqs2brew-0.1.2.dist-info/top_level.txt
reqs2brew-0.1.2.dist-info/RECORD
