Metadata-Version: 2.4
Name: reqs2brew
Version: 0.1.2
Summary: A tool to generate Homebrew resource blocks from PyPI packages
Author-email: Biao Jiang <github@minsignal.com>
License: MIT
Project-URL: Homepage, https://github.com/biaojiang/homebrew-mdviewer
Project-URL: Documentation, https://github.com/biaojiang/homebrew-mdviewer#readme
Project-URL: Source, https://github.com/biaojiang/homebrew-mdviewer
Project-URL: Issues, https://github.com/biaojiang/homebrew-mdviewer/issues
Keywords: homebrew,cli,formula,resources,brew,python
Classifier: License :: OSI Approved :: MIT License
Classifier: Programming Language :: Python :: 3
Classifier: Topic :: Utilities
Classifier: Environment :: Console
Classifier: Operating System :: OS Independent
Classifier: Natural Language :: English
Requires-Python: >=3.8
License-File: LICENSE
Requires-Dist: requests
Requires-Dist: packaging
Dynamic: license-file
